dworshak_access/__init__.py
dworshak_access/vault.py
dworshak_access-0.1.11.dist-info/licenses/LICENSE
dworshak_access-0.1.11.dist-info/METADATA
dworshak_access-0.1.11.dist-info/WHEEL
dworshak_access-0.1.11.dist-info/top_level.txt
dworshak_access-0.1.11.dist-info/RECORD
