Metadata-Version: 2.4
Name: dworshak-access
Version: 0.1.11
Summary: **dworshak-access** is a light-weight library for local credential access. It exposes the **get_secret()** function, to allow a program to leverage credentials that have been established using the Drowshak CLI tool, which is a separate package.
Requires-Python: >=3.9
License-File: LICENSE
Requires-Dist: cryptography>=46.0.3
Dynamic: license-file
